{"name":"Schule für geistig Behinderte  \"Johanne Nathusius \"   (Schule in freier Trägerschaft)","id":"SN-4320040","address":" Alte Hauptstraße 36a 01561 Großenhain OT Skäßchen  ","school_type":"Schule für geistig Behinderte","legal_status":1,"fax":"03522/528734 ","phone":"03522/502520 ","website":"http://www.diakonie-grossenhain.de/pages/fschule.html","email":"foerderschule@diakonie-grossenhain.de","provider":"Diakonie Riesa-Großenhain gGmbH -Geschäftsstelle","director":"Frau Seifert, Eva-Maria"}
